log_to_db/__init__.py
log_to_db/db_log.py
log_to_db/duckdb_log.py
log_to_db/exceptions.py
log_to_db/postgres_log.py
log_to_db/sqlite_log.py
log_to_db/struct_logging.py
log_to_db-0.3.0.dist-info/METADATA
log_to_db-0.3.0.dist-info/WHEEL
log_to_db-0.3.0.dist-info/licenses/LICENSE
log_to_db-0.3.0.dist-info/RECORD
