Metadata-Version: 2.4
Name: log_to_db
Version: 0.3.0
Dynamic: Summary
Project-URL: Home, https://github.com/cetyler/log_to_db/wiki
Author: Christopher Tyler
License-File: LICENSE
Requires-Python: >=3.11
Requires-Dist: duckdb>=1.3.0
Requires-Dist: psycopg[binary]
